http_servers/__init__.py
http_servers/__main__.py
http_servers/commands.py
http_servers/options.py
http_servers/parser.py
http_servers-0.0.2.dist-info/METADATA
http_servers-0.0.2.dist-info/WHEEL
http_servers-0.0.2.dist-info/entry_points.txt
http_servers-0.0.2.dist-info/top_level.txt
http_servers-0.0.2.dist-info/RECORD
