Metadata-Version: 2.1
Name: http-servers
Version: 0.0.2
Summary: http-servers is a simple, no-dependencies command-line static HTTP server.
